django_cloud_deployer/__init__.py
django_cloud_deployer/__main__.py
django_cloud_deployer/azure.py
django_cloud_deployer/command_runner.py
django_cloud_deployer/configs.py
django_cloud_deployer/heroku.py
django_cloud_deployer/main.py
django_cloud_deployer/provider.py
django_cloud_deployer/providers.py
django_cloud_deployer/urls_annotator.py
django_cloud_deployer/config_files/azure/cloud_router.py
django_cloud_deployer/config_files/azure/host.json
django_cloud_deployer/config_files/azure/package-lock.json
django_cloud_deployer/config_files/azure/package.json
django_cloud_deployer/config_files/azure/serverless.yml
django_cloud_deployer/config_files/heroku/Procfile
django_cloud_deployer-1.0.2.dist-info/METADATA
django_cloud_deployer-1.0.2.dist-info/WHEEL
django_cloud_deployer-1.0.2.dist-info/top_level.txt
django_cloud_deployer-1.0.2.dist-info/RECORD
