Metadata-Version: 2.1
Name: django-cloud-deployer
Version: 1.0.2
Summary: Hybrid cloud deployment (IaaS/PaaS and FaaS) of Django web applications.
Home-page: UNKNOWN
Author: Rui Alves
License: UNKNOWN
Platform: UNKNOWN
Classifier: Programming Language :: Python
Classifier: Programming Language :: Python :: 3
Classifier: Programming Language :: Python :: 3.8
Requires-Dist: Django (>=3.1.7)
Requires-Dist: asgiref (>=3.3.4)
Requires-Dist: azf-wsgi (>=0.3.1)
Requires-Dist: azure-functions-worker (>=1.1.9)
Requires-Dist: azure-functions (>=1.7.0)
Requires-Dist: chevron (>=0.14.0)
Requires-Dist: grpcio-tools (>=1.33.2)
Requires-Dist: grpcio (>=1.33.2)
Requires-Dist: protobuf (>=3.16.0)
Requires-Dist: pytz (>=2021.1)
Requires-Dist: six (>=1.16.0)
Requires-Dist: sqlparse (>=0.4.1)
Requires-Dist: termcolor (>=1.1.0)
